LICENSE.txt
MANIFEST.in
README.rst
requirements.txt
setup.cfg
setup.py
examples/__init__.py
examples/classifier_accuracy.py
examples/email_classify.py
examples/test_dataset/ham/5458.2001-04-25.kaminski.ham.txt
examples/test_dataset/ham/5459.2001-04-25.kaminski.ham.txt
examples/test_dataset/ham/5460.2001-04-25.kaminski.ham.txt
examples/test_dataset/ham/5461.2001-04-25.kaminski.ham.txt
examples/test_dataset/ham/5462.2001-04-25.kaminski.ham.txt
examples/test_dataset/ham/5463.2001-04-25.kaminski.ham.txt
examples/test_dataset/ham/5465.2001-04-25.kaminski.ham.txt
examples/test_dataset/ham/5466.2001-04-25.kaminski.ham.txt
examples/test_dataset/ham/5468.2001-04-25.kaminski.ham.txt
examples/test_dataset/ham/5469.2001-04-25.kaminski.ham.txt
examples/test_dataset/ham/5472.2001-04-25.kaminski.ham.txt
examples/test_dataset/ham/5474.2001-04-25.kaminski.ham.txt
examples/test_dataset/ham/5476.2001-04-25.kaminski.ham.txt
examples/test_dataset/ham/5477.2001-04-25.kaminski.ham.txt
examples/test_dataset/ham/5480.2001-04-25.kaminski.ham.txt
examples/test_dataset/ham/5481.2001-04-25.kaminski.ham.txt
examples/test_dataset/ham/5483.2001-04-25.kaminski.ham.txt
examples/test_dataset/ham/5484.2001-04-25.kaminski.ham.txt
examples/test_dataset/ham/5486.2001-04-25.kaminski.ham.txt
examples/test_dataset/ham/5487.2001-04-25.kaminski.ham.txt
examples/test_dataset/ham/5489.2001-04-26.kaminski.ham.txt
examples/test_dataset/ham/5490.2001-04-26.kaminski.ham.txt
examples/test_dataset/ham/5491.2001-04-26.kaminski.ham.txt
examples/test_dataset/ham/5492.2001-04-26.kaminski.ham.txt
examples/test_dataset/ham/5493.2001-04-26.kaminski.ham.txt
examples/test_dataset/ham/5494.2001-04-26.kaminski.ham.txt
examples/test_dataset/ham/5495.2001-04-26.kaminski.ham.txt
examples/test_dataset/ham/5496.2001-04-26.kaminski.ham.txt
examples/test_dataset/ham/5498.2001-04-26.kaminski.ham.txt
examples/test_dataset/ham/5499.2001-04-26.kaminski.ham.txt
examples/test_dataset/ham/5500.2001-04-26.kaminski.ham.txt
spammy.egg-info/PKG-INFO
spammy.egg-info/SOURCES.txt
spammy.egg-info/dependency_links.txt
spammy.egg-info/requires.txt
spammy.egg-info/top_level.txt