Metadata-Version: 1.1
Name: spammy
Version: 1.0.2
Summary: spammy: Spam filtering at your service
Home-page: https://github.com/prodicus/spammy
Author: Tasdik Rahman
Author-email: prodicus@outlook.com
License: GPLv3
Download-URL: https://github.com/prodicus/spammy/tarball/1.0.2
Keywords: spam filtering,spam,ham,machine learning,artificial intelligence
Platform: UNKNOWN
Classifier: Development Status :: 3 - Alpha
Classifier: Intended Audience :: Developers
Classifier: Programming Language :: Python :: 3
